{
    "aws-datacenters": {
        "branch": "master",
        "description": "AWS Regional Data Centers mapping",
        "homepage": "https://www.turnkeylinux.org",
        "owner": "turnkeylinux",
        "repo": "aws-datacenters",
        "rev": "a7106906e60969e917e555fd770454f72c78bb75",
        "sha256": "0l6k6cspsb5cil5s2vypm9v7ci798x4q2zv6hyavlvwy1g2gnggf",
        "type": "tarball",
        "url": "https://github.com/turnkeylinux/aws-datacenters/archive/a7106906e60969e917e555fd770454f72c78bb75.tar.gz",
        "url_template": "https://github.com/<owner>/<repo>/archive/<rev>.tar.gz"
    },
    "cardano-db-sync-12": {
        "branch": "refs/tags/12.0.2",
        "description": "A component that follows the Cardano chain and stores blocks and transactions in PostgreSQL",
        "homepage": "",
        "owner": "input-output-hk",
        "repo": "cardano-db-sync",
        "rev": "935e1fe5d5d11d694e9b6c54030a592b85742671",
        "sha256": "1jc4gda82z1xh81p9xl83blbsfsbr556k1ksqfl80fjrhbycaw29",
        "type": "tarball",
        "url": "https://github.com/input-output-hk/cardano-db-sync/archive/935e1fe5d5d11d694e9b6c54030a592b85742671.tar.gz",
        "url_template": "https://github.com/<owner>/<repo>/archive/<rev>.tar.gz"
    },
    "cardano-db-sync-service": {
        "branch": "master",
        "description": "A component that follows the Cardano chain and stores blocks and transactions in PostgreSQL",
        "homepage": "",
        "owner": "input-output-hk",
        "repo": "cardano-db-sync",
        "rev": "c45b954d8a889b1e977c024e61dea2f166d7f40b",
        "sha256": "16di7ddrh1n604nbvmpl5lmrsx6c6rhxlfvcxhcip41v9rlkvcl9",
        "type": "tarball",
        "url": "https://github.com/input-output-hk/cardano-db-sync/archive/c45b954d8a889b1e977c024e61dea2f166d7f40b.tar.gz",
        "url_template": "https://github.com/<owner>/<repo>/archive/<rev>.tar.gz"
    },
    "cardano-explorer-app-1.6": {
        "branch": "refs/tags/1.6.0",
        "description": "Cardano Explorer App",
        "homepage": "",
        "owner": "input-output-hk",
        "repo": "cardano-explorer-app",
        "rev": "80be1db48710067664b2e62ba332192e9c84261a",
        "sha256": "0sx583488yd62bh79vn6ghrwkh1dw3x6gacpy12km4rinr14d8gz",
        "type": "tarball",
        "url": "https://github.com/input-output-hk/cardano-explorer-app/archive/80be1db48710067664b2e62ba332192e9c84261a.tar.gz",
        "url_template": "https://github.com/<owner>/<repo>/archive/<rev>.tar.gz"
    },
    "cardano-faucet": {
        "branch": "alonzo-wallet",
        "description": "Faucet for Cardano",
        "homepage": null,
        "owner": "input-output-hk",
        "repo": "cardano-faucet",
        "rev": "cd00d79764792a095ae653aa29f0601028a650be",
        "sha256": "0jz1aka16klfwwzgvh88q1a3c7gcp5ms5xvjnmkw6cwcd6bm5m1a",
        "type": "tarball",
        "url": "https://github.com/input-output-hk/cardano-faucet/archive/cd00d79764792a095ae653aa29f0601028a650be.tar.gz",
        "url_template": "https://github.com/<owner>/<repo>/archive/<rev>.tar.gz"
    },
    "cardano-graphql-6.1": {
        "branch": "6.1.0-systemd-exec",
        "description": "GraphQL API for Cardano",
        "homepage": "",
        "owner": "input-output-hk",
        "repo": "cardano-graphql",
        "rev": "38eb52b24d3ce977f78fe8ad9682e5c9adfe7633",
        "sha256": "1rz0hi0mzhlwkkz2njzxx7ip2rmrajcxgyj9w90wcfbn4alz3gj7",
        "type": "tarball",
        "url": "https://github.com/input-output-hk/cardano-graphql/archive/38eb52b24d3ce977f78fe8ad9682e5c9adfe7633.tar.gz",
        "url_template": "https://github.com/<owner>/<repo>/archive/<rev>.tar.gz"
    },
    "cardano-graphql-6.2": {
        "branch": "6.2.0-systemd-exec",
        "description": "GraphQL API for Cardano",
        "homepage": "",
        "owner": "input-output-hk",
        "repo": "cardano-graphql",
        "rev": "7e17365d625a152bf97e71225348538b65cbce37",
        "sha256": "0pypvcihrss76cwv4c25c1xcxf5lqfdq0i3n3b0blv1ajxllnjd4",
        "type": "tarball",
        "url": "https://github.com/input-output-hk/cardano-graphql/archive/7e17365d625a152bf97e71225348538b65cbce37.tar.gz",
        "url_template": "https://github.com/<owner>/<repo>/archive/<rev>.tar.gz"
    },
    "cardano-node": {
        "branch": "release/1.34",
        "description": null,
        "homepage": null,
        "owner": "input-output-hk",
        "repo": "cardano-node",
        "rev": "be199b63fa37af77690ecb3e65b235594c965617",
        "sha256": "0vpgyyp5119x1r5vab7m41dd5zggm7m2vs119p1y0di9lgdxvabm",
        "type": "tarball",
        "url": "https://github.com/input-output-hk/cardano-node/archive/be199b63fa37af77690ecb3e65b235594c965617.tar.gz",
        "url_template": "https://github.com/<owner>/<repo>/archive/<rev>.tar.gz"
    },
    "cardano-node-1-33-0rc3": {
        "branch": "refs/tags/1.33.0-rc1",
        "description": "The core component that is used to participate in a Cardano decentralised blockchain.",
        "homepage": "https://cardano.org",
        "owner": "input-output-hk",
        "repo": "cardano-node",
        "rev": "6d4f85e640b686c375d74ba88d534ce931f61589",
        "sha256": "15c8wbfbmbk6cqzc7zwxkixfr7wrvkl3bl9b7lgkdfpvp2x67fgk",
        "type": "tarball",
        "url": "https://github.com/input-output-hk/cardano-node/archive/6d4f85e640b686c375d74ba88d534ce931f61589.tar.gz",
        "url_template": "https://github.com/<owner>/<repo>/archive/<rev>.tar.gz"
    },
    "cardano-node-1.33": {
        "branch": "refs/tags/1.33.0",
        "description": "The core component that is used to participate in a Cardano decentralised blockchain.",
        "homepage": "https://cardano.org",
        "owner": "input-output-hk",
        "repo": "cardano-node",
        "rev": "814df2c146f5d56f8c35a681fe75e85b905aed5d",
        "sha256": "1hr00wqzmcyc3x0kp2hyw78rfmimf6z4zd4vv85b9zv3nqbjgrik",
        "type": "tarball",
        "url": "https://github.com/input-output-hk/cardano-node/archive/814df2c146f5d56f8c35a681fe75e85b905aed5d.tar.gz",
        "url_template": "https://github.com/<owner>/<repo>/archive/<rev>.tar.gz"
    },
    "cardano-node-adopt-metrics": {
        "branch": "karknu/1.33.0_block_adopion_delay",
        "description": "The core component that is used to participate in a Cardano decentralised blockchain.",
        "homepage": "https://cardano.org",
        "owner": "input-output-hk",
        "repo": "cardano-node",
        "rev": "30e16fa136321e7cce73906cc891344df364558a",
        "sha256": "098wwwj99jqdrn3zhsyfj920hks7znxwvx4iwvkl4k0n409rpm33",
        "type": "tarball",
        "url": "https://github.com/input-output-hk/cardano-node/archive/30e16fa136321e7cce73906cc891344df364558a.tar.gz",
        "url_template": "https://github.com/<owner>/<repo>/archive/<rev>.tar.gz"
    },
    "cardano-node-next": {
        "branch": "release/1.34",
        "description": "The core component that is used to participate in a Cardano decentralised blockchain.",
        "homepage": "https://cardano.org",
        "owner": "input-output-hk",
        "repo": "cardano-node",
        "rev": "be199b63fa37af77690ecb3e65b235594c965617",
        "sha256": "0vpgyyp5119x1r5vab7m41dd5zggm7m2vs119p1y0di9lgdxvabm",
        "type": "tarball",
        "url": "https://github.com/input-output-hk/cardano-node/archive/be199b63fa37af77690ecb3e65b235594c965617.tar.gz",
        "url_template": "https://github.com/<owner>/<repo>/archive/<rev>.tar.gz"
    },
    "cardano-node-service": {
        "branch": "p2p-master",
        "description": "The core component that is used to participate in a Cardano decentralised blockchain.",
        "homepage": "https://cardano.org",
        "owner": "input-output-hk",
        "repo": "cardano-node",
        "rev": "f3dfc1d63ad184dca77331384cbc4d9d54311962",
        "sha256": "0wir5ljxw608lp7r0mhvnk7xypb7s4i6id66ga30vcsr2v14nh6q",
        "type": "tarball",
        "url": "https://github.com/input-output-hk/cardano-node/archive/f3dfc1d63ad184dca77331384cbc4d9d54311962.tar.gz",
        "url_template": "https://github.com/<owner>/<repo>/archive/<rev>.tar.gz"
    },
    "cardano-rosetta-1.6": {
        "branch": "refs/tags/1.6.1",
        "description": "An implementation of Rosetta for Cardano ",
        "homepage": "https://www.rosetta-api.org",
        "owner": "input-output-hk",
        "repo": "cardano-rosetta",
        "rev": "d21b40ab21cf8804a33a36454271c8f3a688a4d1",
        "sha256": "10pf7crjn6x287k53gppfmbgy6xsr1yf4fak962wjywxq6x6vxab",
        "type": "tarball",
        "url": "https://github.com/input-output-hk/cardano-rosetta/archive/d21b40ab21cf8804a33a36454271c8f3a688a4d1.tar.gz",
        "url_template": "https://github.com/<owner>/<repo>/archive/<rev>.tar.gz"
    },
    "cardano-rosetta-1.7": {
        "branch": "refs/tags/1.7.0",
        "description": "An implementation of Rosetta for Cardano ",
        "homepage": "https://www.rosetta-api.org",
        "owner": "input-output-hk",
        "repo": "cardano-rosetta",
        "rev": "2a40528f26ab3f2a217be98cd0299c29f270fde2",
        "sha256": "1jmns14mb7v924ixbr7f8rwfqqg44bpgqb8386cjd9p93ldr85wj",
        "type": "tarball",
        "url": "https://github.com/input-output-hk/cardano-rosetta/archive/2a40528f26ab3f2a217be98cd0299c29f270fde2.tar.gz",
        "url_template": "https://github.com/<owner>/<repo>/archive/<rev>.tar.gz"
    },
    "cardano-wallet": {
        "branch": "refs/tags/v2021-09-29",
        "description": "HTTP server & command-line for managing UTxOs and HD wallets in Cardano.",
        "homepage": "",
        "owner": "input-output-hk",
        "repo": "cardano-wallet",
        "rev": "6626489542ce442a8451fb46fb5339346e62b4ee",
        "sha256": "0n1vgbz3m73v33462ifg3qas9djwlpcvi1m0qxc7j15l3w5qhlw5",
        "type": "tarball",
        "url": "https://github.com/input-output-hk/cardano-wallet/archive/6626489542ce442a8451fb46fb5339346e62b4ee.tar.gz",
        "url_template": "https://github.com/<owner>/<repo>/archive/<rev>.tar.gz"
    },
    "flake-compat": {
        "branch": "fixes",
        "description": null,
        "homepage": null,
        "owner": "input-output-hk",
        "repo": "flake-compat",
        "rev": "20f79e3976b76a37090fbeec7b49dc08dac96b8e",
        "sha256": "1lq1a2hrzcmybzxkl0qpzaylgzn4qpw6nngs5qggddgnawp1klkn",
        "type": "tarball",
        "url": "https://github.com/input-output-hk/flake-compat/archive/20f79e3976b76a37090fbeec7b49dc08dac96b8e.tar.gz",
        "url_template": "https://github.com/<owner>/<repo>/archive/<rev>.tar.gz"
    },
    "iohk-nix": {
        "branch": "master",
        "description": "nix scripts shared across projects",
        "homepage": null,
        "owner": "input-output-hk",
        "repo": "iohk-nix",
        "rev": "8e65ca078e00b2138c77f1a2739d394ccfe4a5e7",
        "sha256": "084abfng9maldqqlr7bvrvqz1blblcnxkrx415jhwf7y5zfk5v8q",
        "type": "tarball",
        "url": "https://github.com/input-output-hk/iohk-nix/archive/8e65ca078e00b2138c77f1a2739d394ccfe4a5e7.tar.gz",
        "url_template": "https://github.com/<owner>/<repo>/archive/<rev>.tar.gz"
    },
    "nixpkgs": {
        "branch": "nixos-21.11",
        "description": "Nix Packages collection",
        "homepage": null,
        "owner": "NixOS",
        "repo": "nixpkgs",
        "rev": "b3d86c56c786ad9530f1400adbd4dfac3c42877b",
        "sha256": "09nslcjdgwwb6j9alxrsnq1wvhifq1nmzl2w02l305j0wsmgdial",
        "type": "tarball",
        "url": "https://github.com/NixOS/nixpkgs/archive/b3d86c56c786ad9530f1400adbd4dfac3c42877b.tar.gz",
        "url_template": "https://github.com/<owner>/<repo>/archive/<rev>.tar.gz"
    },
    "offchain-metadata-tools": {
        "branch": "deps-bump",
        "description": "Tools for creating, submitting, and managing off-chain metadata such as multi-asset token metadata",
        "homepage": "",
        "owner": "input-output-hk",
        "repo": "offchain-metadata-tools",
        "rev": "5ed1b19f1d1329a60bafeb12c31edc3e42669a99",
        "sha256": "12gm3rwd1diadhvc7djwf9n891b5kknbid8zayjaslf82pb327gp",
        "type": "tarball",
        "url": "https://github.com/input-output-hk/offchain-metadata-tools/archive/5ed1b19f1d1329a60bafeb12c31edc3e42669a99.tar.gz",
        "url_template": "https://github.com/<owner>/<repo>/archive/<rev>.tar.gz"
    },
    "ogmios-4.2": {
        "branch": "nixos-service",
        "description": "❇️ A WebSocket JSON/RPC bridge for Cardano",
        "homepage": "https://ogmios.dev",
        "owner": "input-output-hk",
        "repo": "cardano-ogmios",
        "rev": "e5a08bed31c6084ffd38b5788be1fc93c80b13e2",
        "sha256": "1a63cydpvfm8in0lh1qy3lbx22gk9ivpxxiycw7dnnc1f3qg66m7",
        "type": "tarball",
        "url": "https://github.com/input-output-hk/cardano-ogmios/archive/e5a08bed31c6084ffd38b5788be1fc93c80b13e2.tar.gz",
        "url_template": "https://github.com/<owner>/<repo>/archive/<rev>.tar.gz"
    },
    "ogmios-5.1": {
        "branch": "nixos-service",
        "description": "❇️ A WebSocket JSON/RPC bridge for Cardano",
        "homepage": "https://ogmios.dev",
        "owner": "input-output-hk",
        "repo": "cardano-ogmios",
        "rev": "101de744a9a29534cbf078b7b54fc122b4609b9e",
        "sha256": "1vphgb71bzl8dy5b039502xb0n93pcx2srysr4qv5q9rgg4ww6ay",
        "type": "tarball",
        "url": "https://github.com/input-output-hk/cardano-ogmios/archive/101de744a9a29534cbf078b7b54fc122b4609b9e.tar.gz",
        "url_template": "https://github.com/<owner>/<repo>/archive/<rev>.tar.gz"
    },
    "ops-lib": {
        "branch": "master",
        "description": "NixOps deployment configuration library for IOHK devops ",
        "homepage": null,
        "owner": "input-output-hk",
        "repo": "ops-lib",
        "rev": "c12558d54c9306b6917821e3e594148e4bd1eac4",
        "sha256": "1ic2i2jhnmyxg2fvh5wy4b3wmn9akc6xvzgzjblfxxhmksayfhzl",
        "type": "tarball",
        "url": "https://github.com/input-output-hk/ops-lib/archive/c12558d54c9306b6917821e3e594148e4bd1eac4.tar.gz",
        "url_template": "https://github.com/<owner>/<repo>/archive/<rev>.tar.gz"
    }
}
